flask_confighelper.py
flask_confighelper-1.0.0.dist-info/DESCRIPTION.rst
flask_confighelper-1.0.0.dist-info/METADATA
flask_confighelper-1.0.0.dist-info/RECORD
flask_confighelper-1.0.0.dist-info/WHEEL
flask_confighelper-1.0.0.dist-info/metadata.json
flask_confighelper-1.0.0.dist-info/top_level.txt
