Metadata-Version: 2.0
Name: flask-confighelper
Version: 1.0.0
Summary: Helper for setting up environment configurations
Home-page: https://github.com/byt3smith/flask-confighelper
Author: Bob Argenbright
Author-email: UNKNOWN
License: MIT License
Platform: any
Classifier: Environment :: Web Environment
Classifier: Intended Audience :: Developers
Classifier: License :: OSI Approved :: MIT License
Classifier: Operating System :: OS Independent
Classifier: Programming Language :: Python
Classifier: Topic :: Internet :: WWW/HTTP :: Dynamic Content
Classifier: Topic :: Software Development :: Libraries :: Python Modules
Requires-Dist: Flask
